{"symbol": "CRAFTSMAN", "name": "CRAFTSMAN", "series": [{"date": "2026-05-11", "open": 9039.5, "high": 9275.0, "low": 8736.5, "close": 8806.0, "volume": 651559.0, "ema9": 8806.0, "bb_middle": null, "bb_upper": null, "bb_lower": null, "vwap": 8939.166666666666}, {"date": "2026-05-12", "open": 8868.0, "high": 9054.0, "low": 8601.0, "close": 8688.0, "volume": 200188.0, "ema9": 8782.4, "bb_middle": null, "bb_upper": null, "bb_lower": null, "vwap": 8781.0}, {"date": "2026-05-13", "open": 8632.5, "high": 8845.0, "low": 8512.5, "close": 8584.5, "volume": 65958.0, "ema9": 8742.82, "bb_middle": null, "bb_upper": null, "bb_lower": null, "vwap": 8647.333333333334}, {"date": "2026-05-14", "open": 8695.0, "high": 8761.0, "low": 8513.5, "close": 8567.0, "volume": 61274.0, "ema9": 8707.656, "bb_middle": null, "bb_upper": null, "bb_lower": null, "vwap": 8613.833333333334}, {"date": "2026-05-15", "open": 8566.5, "high": 8760.0, "low": 8320.0, "close": 8462.5, "volume": 70403.0, "ema9": 8658.624800000001, "bb_middle": null, "bb_upper": null, "bb_lower": null, "vwap": 8514.166666666666}, {"date": "2026-05-18", "open": 8472.5, "high": 8499.0, "low": 8242.5, "close": 8428.5, "volume": 38689.0, "ema9": 8612.599840000003, "bb_middle": null, "bb_upper": null, "bb_lower": null, "vwap": 8390.0}, {"date": "2026-05-19", "open": 8400.0, "high": 8564.0, "low": 8351.5, "close": 8536.0, "volume": 30925.0, "ema9": 8597.279872000003, "bb_middle": null, "bb_upper": null, "bb_lower": null, "vwap": 8483.833333333334}, {"date": "2026-05-20", "open": 8496.5, "high": 8619.0, "low": 8401.0, "close": 8575.0, "volume": 38814.0, "ema9": 8592.823897600003, "bb_middle": null, "bb_upper": null, "bb_lower": null, "vwap": 8531.666666666666}, {"date": "2026-05-21", "open": 8620.0, "high": 8650.0, "low": 8520.0, "close": 8543.0, "volume": 35973.0, "ema9": 8582.859118080003, "bb_middle": null, "bb_upper": null, "bb_lower": null, "vwap": 8571.0}, {"date": "2026-05-22", "open": 8543.0, "high": 8774.0, "low": 8425.0, "close": 8702.0, "volume": 45785.0, "ema9": 8606.687294464004, "bb_middle": null, "bb_upper": null, "bb_lower": null, "vwap": 8633.666666666666}, {"date": "2026-05-25", "open": 8850.0, "high": 8919.0, "low": 8625.5, "close": 8692.5, "volume": 33663.0, "ema9": 8623.849835571204, "bb_middle": null, "bb_upper": null, "bb_lower": null, "vwap": 8745.666666666666}, {"date": "2026-05-26", "open": 8666.5, "high": 8843.0, "low": 8622.0, "close": 8667.5, "volume": 24446.0, "ema9": 8632.579868456964, "bb_middle": null, "bb_upper": null, "bb_lower": null, "vwap": 8710.833333333334}, {"date": "2026-05-27", "open": 8660.0, "high": 8787.5, "low": 8570.5, "close": 8688.5, "volume": 31339.0, "ema9": 8643.763894765572, "bb_middle": null, "bb_upper": null, "bb_lower": null, "vwap": 8682.166666666666}, {"date": "2026-05-28", "open": 8688.5, "high": 8688.5, "low": 8688.5, "close": 8688.5, "volume": 0, "ema9": 8652.711115812459, "bb_middle": null, "bb_upper": null, "bb_lower": null, "vwap": 8688.5}, {"date": "2026-05-29", "open": 8830.0, "high": 9259.0, "low": 8748.5, "close": 9074.0, "volume": 135231.0, "ema9": 8736.968892649968, "bb_middle": null, "bb_upper": null, "bb_lower": null, "vwap": 9027.166666666666}, {"date": "2026-06-01", "open": 9178.0, "high": 9232.0, "low": 8589.0, "close": 8771.5, "volume": 205545.0, "ema9": 8743.875114119975, "bb_middle": null, "bb_upper": null, "bb_lower": null, "vwap": 8864.166666666666}, {"date": "2026-06-02", "open": 8687.5, "high": 9000.0, "low": 8675.0, "close": 8979.0, "volume": 42669.0, "ema9": 8790.900091295982, "bb_middle": null, "bb_upper": null, "bb_lower": null, "vwap": 8884.666666666666}, {"date": "2026-06-03", "open": 8978.0, "high": 9001.0, "low": 8613.5, "close": 8898.5, "volume": 95289.0, "ema9": 8812.420073036787, "bb_middle": null, "bb_upper": null, "bb_lower": null, "vwap": 8837.666666666666}, {"date": "2026-06-04", "open": 8878.0, "high": 9300.0, "low": 8843.5, "close": 9174.0, "volume": 86273.0, "ema9": 8884.73605842943, "bb_middle": null, "bb_upper": null, "bb_lower": null, "vwap": 9105.833333333334}, {"date": "2026-06-05", "open": 9200.5, "high": 9289.0, "low": 9033.5, "close": 9065.0, "volume": 37933.0, "ema9": 8920.788846743544, "bb_middle": 8729.575, "bb_upper": 9140.359039977211, "bb_lower": 8318.79096002279, "vwap": 9129.166666666666}, {"date": "2026-06-08", "open": 9031.0, "high": 9178.0, "low": 8871.5, "close": 8976.0, "volume": 44832.0, "ema9": 8931.831077394836, "bb_middle": 8738.075, "bb_upper": 9161.66846961444, "bb_lower": 8314.481530385561, "vwap": 9008.5}, {"date": "2026-06-09", "open": 8976.0, "high": 9200.5, "low": 8900.0, "close": 9126.5, "volume": 66943.0, "ema9": 8970.764861915868, "bb_middle": 8760.0, "bb_upper": 9215.172384926853, "bb_lower": 8304.827615073147, "vwap": 9075.666666666666}, {"date": "2026-06-10", "open": 9154.0, "high": 9154.0, "low": 8934.0, "close": 8986.5, "volume": 63168.0, "ema9": 8973.911889532694, "bb_middle": 8780.1, "bb_upper": 9237.993284510701, "bb_lower": 8322.2067154893, "vwap": 9024.833333333334}, {"date": "2026-06-11", "open": 8922.0, "high": 8948.0, "low": 8683.5, "close": 8792.5, "volume": 85657.0, "ema9": 8937.629511626155, "bb_middle": 8791.375, "bb_upper": 9238.70730097993, "bb_lower": 8344.04269902007, "vwap": 8808.0}, {"date": "2026-06-12", "open": 8909.0, "high": 9017.0, "low": 8755.5, "close": 8917.5, "volume": 62301.0, "ema9": 8933.603609300924, "bb_middle": 8814.125, "bb_upper": 9237.900515456, "bb_lower": 8390.349484544, "vwap": 8896.666666666666}, {"date": "2026-06-15", "open": 9100.0, "high": 9396.0, "low": 8990.0, "close": 9337.0, "volume": 109175.0, "ema9": 9014.28288744074, "bb_middle": 8859.55, "bb_upper": 9302.574028693702, "bb_lower": 8416.525971306297, "vwap": 9241.0}, {"date": "2026-06-16", "open": 9433.5, "high": 9490.0, "low": 9213.0, "close": 9326.0, "volume": 86572.0, "ema9": 9076.626309952593, "bb_middle": 8899.05, "bb_upper": 9360.143797399183, "bb_lower": 8437.956202600815, "vwap": 9343.0}, {"date": "2026-06-17", "open": 9400.0, "high": 9656.0, "low": 9336.5, "close": 9498.5, "volume": 140241.0, "ema9": 9161.001047962076, "bb_middle": 8945.225, "bb_upper": 9450.146129979723, "bb_lower": 8440.303870020278, "vwap": 9497.0}, {"date": "2026-06-18", "open": 9520.0, "high": 9628.0, "low": 9457.5, "close": 9500.0, "volume": 37642.0, "ema9": 9228.800838369662, "bb_middle": 8993.075, "bb_upper": 9517.46505282328, "bb_lower": 8468.684947176722, "vwap": 9528.5}, {"date": "2026-06-19", "open": 9480.0, "high": 9938.0, "low": 9475.0, "close": 9806.5, "volume": 253361.0, "ema9": 9344.340670695728, "bb_middle": 9048.3, "bb_upper": 9663.257592033793, "bb_lower": 8433.342407966205, "vwap": 9739.833333333334}], "signal": {"ema_above_bb_middle": true, "close_above_bb_upper": true, "ema_crossed_bb_middle": false, "close_crossed_bb_upper": true, "breakout": true, "ready": false, "price_ok": true, "liquidity_ok": false, "volume_ok": true, "avg_volume": 86436, "today_volume": 253361.0, "price": 9806.5, "ema9": 9344.340670695728, "bb_middle": 9048.3, "bb_upper": 9663.257592033793, "bb_lower": 8433.342407966205, "vwap": 9739.833333333334, "date": "2026-06-19"}}